metapype/VERSION.txt
metapype/__init__.py
metapype/changelog.md
metapype/eml/__init__.py
metapype/eml/evaluate.py
metapype/eml/evaluation_warnings.py
metapype/eml/exceptions.py
metapype/eml/export.py
metapype/eml/harness.py
metapype/eml/names.py
metapype/eml/references.py
metapype/eml/rule.py
metapype/eml/rules.json
metapype/eml/rules.py
metapype/eml/validate.py
metapype/eml/validation_errors.py
metapype/model/__init__.py
metapype/model/metapype_io.py
metapype/model/mp_io.py
metapype/model/node.py
metapype/model/normalize.py
metapype-0.1.4.dist-info/METADATA
metapype-0.1.4.dist-info/WHEEL
metapype-0.1.4.dist-info/licenses/LICENSE
metapype-0.1.4.dist-info/RECORD
