Metadata-Version: 2.4
Name: metapype
Version: 0.1.4
Author-email: Mark Servilla <mark.servilla@gmail.com>
License-File: LICENSE
Requires-Python: >=3.11
Provides-Extra: dev
Requires-Dist: hatchling; extra == 'dev'
Requires-Dist: pytest; extra == 'dev'
Requires-Dist: ruff; extra == 'dev'
